my_package/__init__.py
my_package/__main__.py
my_package/echo.py
my_package/sub/__init__.py
my_package/sub/sub.py
edc2019_demo_package-1.0.0.dist-info/LICENSE
edc2019_demo_package-1.0.0.dist-info/METADATA
edc2019_demo_package-1.0.0.dist-info/WHEEL
edc2019_demo_package-1.0.0.dist-info/entry_points.txt
edc2019_demo_package-1.0.0.dist-info/top_level.txt
edc2019_demo_package-1.0.0.dist-info/RECORD
