Metadata-Version: 2.1
Name: edc2019-demo-package
Version: 1.0.0
Summary: my brilliant package
Home-page: UNKNOWN
Author: mechazawa
Author-email: mech@equinor.com
License: UNKNOWN
Platform: UNKNOWN
Requires-Dist: numpy
